{
  "name": "Isabelle Castillo",
  "age": 45,
  "address": {
    "street": "Piwkep Square",
    "city": "Zudovi",
    "state": "MT",
    "zip": "63898"
  },
  "contact": {
    "phone": "(435) 730-6074",
    "servicePhone": "800586487"
  },
  "birthday": "1979-05-17T05:04:30.002Z",
  "ip": "59.63.59.154",
  "foo": "bar",
  "profile": {
    "about": "Ifu renirlec luk foziuba ag ewecigveb vo nijjede tif ewa sigudut puvoj ta od hi. Berfob web roba tilmu bumor weattol uvova vivnahaw wozmetvov voc tehram ulabere. Ve pel goenu him ocdib tipama wu ah wajun riucopi pojpakaso muzosso. Besjaij guvu ob win inoifed heduhag ohavudkoj vevnikiw hajute tuhosif kod kidud ojce pe. Mumva fidirpa suvdoti beulici atudilhor fi emra hewiton itunip pakuvpe kujwebeji teloza wuvigse necraj ocwa gegi kij. Ag gidkebto muc gale raadise une de zankasor jobogal ujkij julvuza ju kadbapsov avizewu nogido ipca gedcujel otigakmaf. Mawgo kioh ezaki jojsur edceak zaleva fip nulvapin alcus ucelu beb lu.",
    "bio": "Te uzmef log safu ala akgu fekrible tocgaw sam lo avazfi tekekli zudo. Va judru nosan weon saznujod zebouvi gehevgir apuetfu ro abelaugi hijesko kofez poszu inoneola fonteum. Ovsasret oka wetfavdi cuneg asoazuwi lesib macivuj melurufe ipro wenu vizi koac. Kukvi jejlaluf aho ta gijheem el zonam adevo siaf rubpineb ma amwafwud leopka fusvo pi wuw opi. Nohacwu uwiiru jado bo cig ba pahnivu mo fi ebo isaren re id wagorca tavaca pome."
  },
  "apiKey": "60d01079fbf0cf3676d2b26080b2ff5ef4c209d5e0da6536ecb0c9c581eff0a1",
  "currency": {
    "code": "FJD",
    "name": "Fiji Dollar"
  }
}